pyhaystack/__init__.py
pyhaystack/exception.py
pyhaystack/info.py
pyhaystack/pyhaystack.py
pyhaystack/pyhaystackTest.py
pyhaystack/browser/__init__.py
pyhaystack/browser/browser.py
pyhaystack/client/__init__.py
pyhaystack/client/loader.py
pyhaystack/client/niagara.py
pyhaystack/client/niagara4.py
pyhaystack/client/niagara4_old.py
pyhaystack/client/session.py
pyhaystack/client/skyspark.py
pyhaystack/client/widesky.py
pyhaystack/client/entity/__init__.py
pyhaystack/client/entity/entity.py
pyhaystack/client/entity/model.py
pyhaystack/client/entity/tags.py
pyhaystack/client/entity/mixins/__init__.py
pyhaystack/client/entity/mixins/equip.py
pyhaystack/client/entity/mixins/point.py
pyhaystack/client/entity/mixins/site.py
pyhaystack/client/entity/mixins/tz.py
pyhaystack/client/entity/models/__init__.py
pyhaystack/client/entity/models/haystack.py
pyhaystack/client/entity/ops/__init__.py
pyhaystack/client/entity/ops/crud.py
pyhaystack/client/http/__init__.py
pyhaystack/client/http/auth.py
pyhaystack/client/http/base.py
pyhaystack/client/http/dummy.py
pyhaystack/client/http/exceptions.py
pyhaystack/client/http/sync.py
pyhaystack/client/mixins/__init__.py
pyhaystack/client/mixins/vendor/__init__.py
pyhaystack/client/mixins/vendor/skyspark/__init__.py
pyhaystack/client/mixins/vendor/skyspark/evalexpr.py
pyhaystack/client/mixins/vendor/widesky/__init__.py
pyhaystack/client/mixins/vendor/widesky/crud.py
pyhaystack/client/mixins/vendor/widesky/multihis.py
pyhaystack/client/ops/__init__.py
pyhaystack/client/ops/entity.py
pyhaystack/client/ops/feature.py
pyhaystack/client/ops/grid.py
pyhaystack/client/ops/his.py
pyhaystack/client/ops/vendor/__init__.py
pyhaystack/client/ops/vendor/niagara.py
pyhaystack/client/ops/vendor/niagara4.py
pyhaystack/client/ops/vendor/niagara4_login.py
pyhaystack/client/ops/vendor/niagaraV4.py
pyhaystack/client/ops/vendor/niagaraV4_work.py
pyhaystack/client/ops/vendor/niagara_scram.py
pyhaystack-0.92.5.dist-info/DESCRIPTION.rst
pyhaystack-0.92.5.dist-info/METADATA
pyhaystack-0.92.5.dist-info/RECORD
pyhaystack-0.92.5.dist-info/WHEEL
pyhaystack-0.92.5.dist-info/metadata.json
pyhaystack-0.92.5.dist-info/top_level.txt
