Metadata-Version: 2.0
Name: pyhaystack
Version: 0.92.5
Summary: Python Haystack Utility
Home-page: http://www.project-haystack.com/
Author: Christian Tremblay, Stuart Longland, @sudo-Whateverman, Igor
Author-email: christian.tremblay@servisys.com
License: UNKNOWN
Keywords: tags,hvac,project-haystack,building,automation,analytic
Platform: UNKNOWN
Classifier: Development Status :: 4 - Beta
Classifier: Intended Audience :: Developers
Classifier: Operating System :: OS Independent
Classifier: Programming Language :: Python
Classifier: Topic :: Software Development :: Libraries :: Python Modules
Classifier: Topic :: System :: Networking
Classifier: Topic :: Utilities
Requires-Dist: certifi
Requires-Dist: fysom
Requires-Dist: hszinc
Requires-Dist: iso8601
Requires-Dist: pandas
Requires-Dist: parsimonious
Requires-Dist: requests
Requires-Dist: semver
Requires-Dist: setuptools
Requires-Dist: signalslot
Requires-Dist: six
